plex_tvdb_alt_orderer/main.py
plex_tvdb_alt_orderer-0.3.1.dist-info/LICENSE
plex_tvdb_alt_orderer-0.3.1.dist-info/METADATA
plex_tvdb_alt_orderer-0.3.1.dist-info/WHEEL
plex_tvdb_alt_orderer-0.3.1.dist-info/entry_points.txt
plex_tvdb_alt_orderer-0.3.1.dist-info/top_level.txt
plex_tvdb_alt_orderer-0.3.1.dist-info/RECORD
