Metadata-Version: 2.1
Name: plex-tvdb-alt-orderer
Version: 0.3.1
Summary: A utility that applies alternate TVDB orders to Plex.
Author: bpoxy
Project-URL: Homepage, https://github.com/bpoxy/plex-tvdb-alt-orderer
Project-URL: Bug Tracker, https://github.com/bpoxy/plex-tvdb-alt-orderer
Classifier: Development Status :: 3 - Alpha
Classifier: License :: OSI Approved :: MIT License
Classifier: Operating System :: OS Independent
Classifier: Programming Language :: Python :: 3
Classifier: Topic :: Multimedia :: Video
Requires-Python: >=3.8
License-File: LICENSE
Requires-Dist: click
Requires-Dist: inquirer
Requires-Dist: plexapi
Requires-Dist: progress
Requires-Dist: termcolor
Requires-Dist: tvdb-v4-official
Requires-Dist: validators
